grokcore.formlib-4.1-py3.12-nspkg.pth
grokcore/formlib/__init__.py
grokcore/formlib/components.py
grokcore/formlib/configure.zcml
grokcore/formlib/formlib.py
grokcore/formlib/ftesting.zcml
grokcore/formlib/interfaces.py
grokcore/formlib/meta.py
grokcore/formlib/meta.zcml
grokcore/formlib/testing.py
grokcore/formlib/templates/default_display_form.pt
grokcore/formlib/templates/default_edit_form.pt
grokcore/formlib/tests/__init__.py
grokcore/formlib/tests/test_base.py
grokcore/formlib/tests/test_functional.py
grokcore/formlib/tests/base/__init__.py
grokcore/formlib/tests/base/form/__init__.py
grokcore/formlib/tests/base/form/customautoform.py
grokcore/formlib/tests/base/form/customform.py
grokcore/formlib/tests/base/form/fields.py
grokcore/formlib/tests/base/form/form.py
grokcore/formlib/tests/base/form/norender.py
grokcore/formlib/tests/base/form/norender2.py
grokcore/formlib/tests/base/form/schemaform.py
grokcore/formlib/tests/base/form/schemainherit.py
grokcore/formlib/tests/functional/__init__.py
grokcore/formlib/tests/functional/form/__init__.py
grokcore/formlib/tests/functional/form/actions.py
grokcore/formlib/tests/functional/form/addform.py
grokcore/formlib/tests/functional/form/addform_applydata.py
grokcore/formlib/tests/functional/form/editform_applydata.py
grokcore/formlib/tests/functional/form/editform_applydata_schema.py
grokcore/formlib/tests/functional/form/editform_applydata_schemafields.py
grokcore/formlib/tests/functional/form/form.py
grokcore/formlib/tests/functional/form/templateform.py
grokcore/formlib/tests/functional/form/update.py
grokcore_formlib-4.1.dist-info/licenses/LICENSE.txt
grokcore_formlib-4.1.dist-info/METADATA
grokcore_formlib-4.1.dist-info/WHEEL
grokcore_formlib-4.1.dist-info/namespace_packages.txt
grokcore_formlib-4.1.dist-info/top_level.txt
grokcore_formlib-4.1.dist-info/RECORD
