Metadata-Version: 2.4
Name: grokcore.formlib
Version: 4.1
Summary: Grok-like configuration for zope.formlib components
Home-page: https://github.com/zopefoundation/grokcore.formlib
Download-URL: https://pypi.org/project/grokcore.formlib
Author: Grok Team
Author-email: zope-dev@zope.dev
License: ZPL
Classifier: Development Status :: 6 - Mature
Classifier: Environment :: Web Environment
Classifier: Framework :: Zope :: 3
Classifier: Intended Audience :: Developers
Classifier: License :: OSI Approved :: Zope Public License
Classifier: Programming Language :: Python
Classifier: Programming Language :: Python :: 3
Classifier: Programming Language :: Python :: 3.9
Classifier: Programming Language :: Python :: 3.10
Classifier: Programming Language :: Python :: 3.11
Classifier: Programming Language :: Python :: 3.12
Classifier: Programming Language :: Python :: 3.13
Classifier: Programming Language :: Python :: Implementation
Classifier: Programming Language :: Python :: Implementation :: CPython
Classifier: Programming Language :: Python :: Implementation :: PyPy
Requires-Python: >=3.9
License-File: LICENSE.txt
Requires-Dist: setuptools
Requires-Dist: grokcore.component>=2.1
Requires-Dist: grokcore.content>=1.2
Requires-Dist: grokcore.security>=1.5
Requires-Dist: grokcore.view>=2.0
Requires-Dist: martian>=0.13
Requires-Dist: pytz
Requires-Dist: zope.container
Requires-Dist: zope.event
Requires-Dist: zope.formlib>=4.3.0
Requires-Dist: zope.interface
Requires-Dist: zope.lifecycleevent
Requires-Dist: zope.publisher
Requires-Dist: zope.schema
Provides-Extra: test
Requires-Dist: zope.app.wsgi[test]; extra == "test"
Requires-Dist: zope.configuration; extra == "test"
Requires-Dist: zope.testbrowser; extra == "test"
Requires-Dist: zope.testing; extra == "test"
Dynamic: author
Dynamic: author-email
Dynamic: classifier
Dynamic: description
Dynamic: download-url
Dynamic: home-page
Dynamic: license
Dynamic: license-file
Dynamic: provides-extra
Dynamic: requires-dist
Dynamic: requires-python
Dynamic: summary
